Workbook

Sheet 前提
B2: 伴走事業 — 経営シミュレーション
B3: 前提（青い数字を打ち替えると、全シートが自動で再計算されます）
B5: ① 滑走路とコスト
B6: 初期キャッシュ（滑走路） | C6: 2000000 | D6: 海外資金の引き出し。月50万×4ヶ月分
B7: 会社の月次固定費（損益分岐） | C7: =C20+C21+C22 -> 183500 | D7: 役員報酬+社保+販管費の自動計算。これを総売上が超えれば会社は黒字
B8: 既存受託（月・当面継続） | C8: 400000 | D8: 立ち上げ期の土台。新事業が育つまでの足場
B10: ② 商品単価
B11: 構造診断・立ち上げ価格 | C11: 100000 | D11: 先着5社の実績協力価格（通常30万）
B12: 構造診断・通常価格 | C12: 300000 | D12: 竹（標準）。松は50万〜
B13: 濃い伴走（月額・1社） | C13: 750000 | D13: 週2日相当。シナリオA
B14: ライト契約（月額・1社） | C14: 70000 | D14: 自走後の継続。相談・保守ベース
B16: ③ 上限（品質を守る方針）
B17: 濃い伴走の同時上限（社） | C17: 3 | D17: 3社を超えると文脈維持の工数が品質を割る
B19: ④ 会計レベル前提（費用・税）
B20: 役員報酬（月） | C20: 70000 | D20: 立ち上げ年は7万で低く固定（定期同額のため期中変更は不可→Y2で増額）。生活は貯蓄で橋渡し
B21: 会社負担 社会保険（月） | C21: 11000 | D21: 役員報酬7万の最低等級 概算
B22: 販管費（月） | C22: 102500 | D22: 税理士・SaaS・通信・交通・交際・学習・広告の合算
B23: 消費税 みなし仕入率（簡易課税） | C23: 0.5 | D23: サービス業=第5種50%。納税=売上消費税×(1-この率)
B24: 消費税率 | C24: 0.1
B25: 法人実効税率（概算） | C25: 0.25 | D25: 所得800万以下の中小法人 概算
B26: 法人住民税 均等割（年・赤字でも発生） | C26: 70000 | D26: 最低限かかる固定税
B28: ⑤ 営業ファネル（登壇・自前コンテンツで新規診断を生む）
B29: 1登壇あたり参加者（人） | C29: 20 | D29: 小規模セミナー/勉強会の集客想定。最初の1〜2回はここが一番難所（要・自前集客）
B30: 参加者→無料相談 化率 | C30: 0.15 | D30: 登壇を聞いた人が個別相談に来る率。温度が高い10〜20%
B31: 無料相談→診断 成約率 | C31: 0.35 | D31: 登壇経由は信頼が乗り30万診断に進みやすい(コールドの28%より高い)
B32: 診断→伴走 移行率 | C32: 0.5 | D32: 断る関門として意図的に絞る。据え置き
B33: 1登壇の所要時間（h/回・定常） | C33: 10 | D33: 資料作成は流用前提。初回のみ別途+約20hの先行投資(ストック資産化＝L-3/L-4)
B34: ⑥ 個人サバイバル（会社とは別の財布）
B35: 個人の貯蓄（滑走路） | C35: 2000000 | D35: 海外資金。会社でなく“あなた個人”の生活を支える
B36: 個人の生活費（月） | C36: 500000 | D36: 家賃・生活・税社保等の個人支出

Sheet Year1_月次
B2: Year 1 — 月次キャッシュ推移
B3: 新事業の「数量」だけ青で打ち替えてください（診断件数・伴走社数・ライト社数）。売上と残高は自動計算。
B5: 項目 | C5: 1月 | D5: 2月 | E5: 3月 | F5: 4月 | G5: 5月 | H5: 6月 | I5: 7月 | J5: 8月 | K5: 9月 | L5: 10月 | M5: 11月 | N5: 12月 | O5: 12月
B6: 診断・件数（立ち上げ価格） | C6: 1 | D6: 1 | E6: 1 | F6: 1 | G6: 0 | H6: 0 | I6: 0 | J6: 0 | K6: 0 | L6: 0 | M6: 0 | N6: 0
B7: 診断・件数（通常価格） | C7: 0 | D7: 0 | E7: 0 | F7: 0 | G7: 0 | H7: 0 | I7: 0 | J7: 1 | K7: 0 | L7: 1 | M7: 0 | N7: 1
B8: 濃い伴走・稼働社数 | C8: 0 | D8: 0 | E8: 0 | F8: 0 | G8: 1 | H8: 1 | I8: 1 | J8: 1 | K8: 2 | L8: 2 | M8: 2 | N8: 2
B9: ライト契約・社数 | C9: 0 | D9: 0 | E9: 0 | F9: 0 | G9: 0 | H9: 0 | I9: 0 | J9: 0 | K9: 0 | L9: 1 | M9: 1 | N9: 1
B11: 新事業 売上 | C11: =C6*前提!$C$11+C7*前提!$C$12+C8*前提!$C$13+C9*前提!$C$14 -> 100000 | D11: =D6*前提!$C$11+D7*前提!$C$12+D8*前提!$C$13+D9*前提!$C$14 -> 100000 | E11: =E6*前提!$C$11+E7*前提!$C$12+E8*前提!$C$13+E9*前提!$C$14 -> 100000 | F11: =F6*前提!$C$11+F7*前提!$C$12+F8*前提!$C$13+F9*前提!$C$14 -> 100000 | G11: =G6*前提!$C$11+G7*前提!$C$12+G8*前提!$C$13+G9*前提!$C$14 -> 750000 | H11: =H6*前提!$C$11+H7*前提!$C$12+H8*前提!$C$13+H9*前提!$C$14 -> 750000 | I11: =I6*前提!$C$11+I7*前提!$C$12+I8*前提!$C$13+I9*前提!$C$14 -> 750000 | J11: =J6*前提!$C$11+J7*前提!$C$12+J8*前提!$C$13+J9*前提!$C$14 -> 1050000 | ... N11: =N6*前提!$C$11+N7*前提!$C$12+N8*前提!$C$13+N9*前提!$C$14 -> 1870000
B12: 既存受託 | C12: =前提!$C$8 -> 400000 | D12: =前提!$C$8 -> 400000 | E12: =前提!$C$8 -> 400000 | F12: =前提!$C$8 -> 400000 | G12: =前提!$C$8 -> 400000 | H12: =前提!$C$8 -> 400000 | I12: =前提!$C$8 -> 400000 | J12: =前提!$C$8 -> 400000 | ... N12: =前提!$C$8 -> 400000
B13: 総売上 | C13: =C11+C12 -> 500000 | D13: =D11+D12 -> 500000 | E13: =E11+E12 -> 500000 | F13: =F11+F12 -> 500000 | G13: =G11+G12 -> 1150000 | H13: =H11+H12 -> 1150000 | I13: =I11+I12 -> 1150000 | J13: =J11+J12 -> 1450000 | ... N13: =N11+N12 -> 2270000
B15: 損益分岐点 | C15: =前提!$C$7 -> 183500 | D15: =前提!$C$7 -> 183500 | E15: =前提!$C$7 -> 183500 | F15: =前提!$C$7 -> 183500 | G15: =前提!$C$7 -> 183500 | H15: =前提!$C$7 -> 183500 | I15: =前提!$C$7 -> 183500 | J15: =前提!$C$7 -> 183500 | ... N15: =前提!$C$7 -> 183500
B16: 単月収支（±） | C16: =C13-C15 -> 316500 | D16: =D13-D15 -> 316500 | E16: =E13-E15 -> 316500 | F16: =F13-F15 -> 316500 | G16: =G13-G15 -> 966500 | H16: =H13-H15 -> 966500 | I16: =I13-I15 -> 966500 | J16: =J13-J15 -> 1266500 | ... N16: =N13-N15 -> 2086500
B17: キャッシュ残高 | C17: =前提!$C$6+C16 -> 2316500 | D17: =C17+D16 -> 2633000 | E17: =D17+E16 -> 2949500 | F17: =E17+F16 -> 3266000 | G17: =F17+G16 -> 4232500 | H17: =G17+H16 -> 5199000 | I17: =H17+I16 -> 6165500 | J17: =I17+J16 -> 7432000 | K17: =J17+K16 -> 9148500 | ... N17: =M17+N16 -> 15108000
B19: 年間 新事業売上 合計 | C19: =SUM(C11:N11) -> 10510000
B20: 年末キャッシュ残高 | C20: =N17 -> 15108000
B21: 初年度の最低残高（滑走路の底） | C21: =MIN(C17:N17) -> 2316500 | D21: ← ここがマイナスにならなければ、負の連鎖で死ぬことはない

Sheet 3年_四半期
B2: 3年計画 — 四半期ショートスパン
B3: 見るのは4つだけ：診断数・伴走社数・ライト社数・キャッシュ残高。指標を増やさないのが一人会社のコツ。
B5: 項目 | C5: Y1Q1 | D5: Y1Q2 | E5: Y1Q3 | F5: Y1Q4 | G5: Y2Q1 | H5: Y2Q2 | I5: Y2Q3 | J5: Y2Q4 | K5: Y3Q1 | L5: Y3Q2 | M5: Y3Q3 | N5: Y3Q4
B6: 診断・件数 / 四半期 | C6: 3 | D6: 2 | E6: 2 | F6: 2 | G6: 2 | H6: 2 | I6: 2 | J6: 2 | K6: 1 | L6: 1 | M6: 1 | N6: 1
B7: 濃い伴走・社数（平均） | C7: 0 | D7: 1 | E7: 1.5 | F7: 2 | G7: 2 | H7: 2 | I7: 2 | J7: 2 | K7: 2 | L7: 2 | M7: 2 | N7: 2
B8: ライト・社数 | C8: 0 | D8: 0 | E8: 0 | F8: 1 | G8: 2 | H8: 3 | I8: 4 | J8: 5 | K8: 6 | L8: 7 | M8: 8 | N8: 9
B10: 新事業 売上 / Q | C10: =C6*前提!$C$11+C7*前提!$C$13*3+C8*前提!$C$14*3 -> 300000 | D10: =D6*前提!$C$11+D7*前提!$C$13*3+D8*前提!$C$14*3 -> 2450000 | E10: =E6*前提!$C$12+E7*前提!$C$13*3+E8*前提!$C$14*3 -> 3975000 | F10: =F6*前提!$C$12+F7*前提!$C$13*3+F8*前提!$C$14*3 -> 5310000 | G10: =G6*前提!$C$12+G7*前提!$C$13*3+G8*前提!$C$14*3 -> 5520000 | H10: =H6*前提!$C$12+H7*前提!$C$13*3+H8*前提!$C$14*3 -> 5730000 | I10: =I6*前提!$C$12+I7*前提!$C$13*3+I8*前提!$C$14*3 -> 5940000 | J10: =J6*前提!$C$12+J7*前提!$C$13*3+J8*前提!$C$14*3 -> 6150000 | K10: =K6*前提!$C$12+K7*前提!$C$13*3+K8*前提!$C$14*3 -> 6060000 | L10: =L6*前提!$C$12+L7*前提!$C$13*3+L8*前提!$C$14*3 -> 6270000 | ... N10: =N6*前提!$C$12+N7*前提!$C$13*3+N8*前提!$C$14*3 -> 6690000
B11: 既存受託 / Q | C11: =前提!$C$8*3 -> 1200000 | D11: =前提!$C$8*3 -> 1200000 | E11: =前提!$C$8*3 -> 1200000 | F11: =前提!$C$8*3 -> 1200000 | G11: =前提!$C$8*3 -> 1200000 | H11: =前提!$C$8*3 -> 1200000 | I11: =前提!$C$8*3 -> 1200000 | J11: =前提!$C$8*3 -> 1200000 | ... N11: =前提!$C$8*3 -> 1200000
B12: 総売上 / Q | C12: =C10+C11 -> 1500000 | D12: =D10+D11 -> 3650000 | E12: =E10+E11 -> 5175000 | F12: =F10+F11 -> 6510000 | G12: =G10+G11 -> 6720000 | H12: =H10+H11 -> 6930000 | I12: =I10+I11 -> 7140000 | J12: =J10+J11 -> 7350000 | ... N12: =N10+N11 -> 7890000
B13: 損益分岐 / Q | C13: =前提!$C$7*3 -> 550500 | D13: =前提!$C$7*3 -> 550500 | E13: =前提!$C$7*3 -> 550500 | F13: =前提!$C$7*3 -> 550500 | G13: =前提!$C$7*3 -> 550500 | H13: =前提!$C$7*3 -> 550500 | I13: =前提!$C$7*3 -> 550500 | J13: =前提!$C$7*3 -> 550500 | ... N13: =前提!$C$7*3 -> 550500
B14: 四半期 収支（±） | C14: =C12-C13 -> 949500 | D14: =D12-D13 -> 3099500 | E14: =E12-E13 -> 4624500 | F14: =F12-F13 -> 5959500 | G14: =G12-G13 -> 6169500 | H14: =H12-H13 -> 6379500 | I14: =I12-I13 -> 6589500 | J14: =J12-J13 -> 6799500 | ... N14: =N12-N13 -> 7339500
B15: 四半期末 キャッシュ残高 | C15: =前提!$C$6+C14 -> 2949500 | D15: =C15+D14 -> 6049000 | E15: =D15+E14 -> 10673500 | F15: =E15+F14 -> 16633000 | G15: =F15+G14 -> 22802500 | H15: =G15+H14 -> 29182000 | I15: =H15+I14 -> 35771500 | J15: =I15+J14 -> 42571000 | K15: =J15+K14 -> 49280500 | ... N15: =M15+N14 -> 70669000
B17: 年間総売上 | C17: =SUM(C12:F12) -> 16835000 | D17: =SUM(G12:J12) -> 28140000 | E17: =SUM(K12:N12) -> 30300000
B18: （C列=Year1, D列=Year2, E列=Year3 の合計）
B22: 年間総売上（C=Y1 / D=Y2 / E=Y3） | C22: =SUM(C12:F12) -> 16835000 | D22: =SUM(G12:J12) -> 28140000 | E22: =SUM(K12:N12) -> 30300000

Sheet 読み方
B2: このモデルの読み方
B4: ■ 何を打ち替えればいいか
B5: ・黄色いセル（青字）だけを変えてください。黒字は自動計算なので触らない。
B6: ・「前提」シートで単価・分岐点・滑走路を変えると、全シートに反映されます。
B7: ・「Year1_月次」「3年_四半期」では、各月/各Qの "数量"（診断件数・伴走社数・ライト社数）を変えます。
B9: ■ どこを見れば「死なない」と分かるか
B10: ・Year1_月次シートの「初年度の最低残高（滑走路の底）」。ここがプラスなら、負の連鎖で資金が尽きることはありません。
B11: ・現在の慎重シナリオでは、底は初月の約190万円。初期200万からほぼ減らずに立ち上がります。
B13: ■ この事業の構造的な強み（数字が示すこと）
B14: ・損益分岐 月50万に対し、既存受託が月40万。埋めるべき差は月10万だけ。
B15: ・診断1社（10万）でその月は分岐点に到達。伴走1社（月75万）に上がれば即黒字。ハードルは低い。
B16: ・濃い伴走は上限3社（品質方針）。3社目以降は売上でなく、資産化・ライト層・1対Nで伸ばす設計。
... B21: ・売上の上振れより、滑走路を守る判断を優先。筋の通らない案件を承認欲で取らない（判断基準に戻る）。

Sheet PL_損益_Y1
B2: Year1 月次 損益計算書（P/L）
B3: 売上は「Year1_月次」から自動リンク（緑字）。費用は「前提」から。消費税は預かりのため売上から除外＝税抜ベース。
B5: 項目 | C5: 1月 | D5: 2月 | E5: 3月 | F5: 4月 | G5: 5月 | H5: 6月 | I5: 7月 | J5: 8月 | K5: 9月 | L5: 10月 | M5: 11月 | N5: 12月 | O5: 年計
B6: 売上高（税抜） | C6: =Year1_月次!C13 -> 500000 | D6: =Year1_月次!D13 -> 500000 | E6: =Year1_月次!E13 -> 500000 | F6: =Year1_月次!F13 -> 500000 | G6: =Year1_月次!G13 -> 1150000 | H6: =Year1_月次!H13 -> 1150000 | I6: =Year1_月次!I13 -> 1150000 | J6: =Year1_月次!J13 -> 1450000 | ... N6: =Year1_月次!N13 -> 2270000 | O6: =SUM(C6:N6) -> 15310000
B8: 役員報酬 | C8: =前提!$C$20 -> 70000 | D8: =前提!$C$20 -> 70000 | E8: =前提!$C$20 -> 70000 | F8: =前提!$C$20 -> 70000 | G8: =前提!$C$20 -> 70000 | H8: =前提!$C$20 -> 70000 | I8: =前提!$C$20 -> 70000 | J8: =前提!$C$20 -> 70000 | ... N8: =前提!$C$20 -> 70000 | O8: =SUM(C8:N8) -> 840000
B9: 法定福利費（社保・会社） | C9: =前提!$C$21 -> 11000 | D9: =前提!$C$21 -> 11000 | E9: =前提!$C$21 -> 11000 | F9: =前提!$C$21 -> 11000 | G9: =前提!$C$21 -> 11000 | H9: =前提!$C$21 -> 11000 | I9: =前提!$C$21 -> 11000 | J9: =前提!$C$21 -> 11000 | ... N9: =前提!$C$21 -> 11000 | O9: =SUM(C9:N9) -> 132000
B10: 販管費 | C10: =前提!$C$22 -> 102500 | D10: =前提!$C$22 -> 102500 | E10: =前提!$C$22 -> 102500 | F10: =前提!$C$22 -> 102500 | G10: =前提!$C$22 -> 102500 | H10: =前提!$C$22 -> 102500 | I10: =前提!$C$22 -> 102500 | J10: =前提!$C$22 -> 102500 | ... N10: =前提!$C$22 -> 102500 | O10: =SUM(C10:N10) -> 1230000
B11: 費用 合計 | C11: =C8+C9+C10 -> 183500 | D11: =D8+D9+D10 -> 183500 | E11: =E8+E9+E10 -> 183500 | F11: =F8+F9+F10 -> 183500 | G11: =G8+G9+G10 -> 183500 | H11: =H8+H9+H10 -> 183500 | I11: =I8+I9+I10 -> 183500 | J11: =J8+J9+J10 -> 183500 | ... N11: =N8+N9+N10 -> 183500 | O11: =SUM(C11:N11) -> 2202000
B13: 営業利益（税引前） | C13: =C6-C11 -> 316500 | D13: =D6-D11 -> 316500 | E13: =E6-E11 -> 316500 | F13: =F6-F11 -> 316500 | G13: =G6-G11 -> 966500 | H13: =H6-H11 -> 966500 | I13: =I6-I11 -> 966500 | J13: =J6-J11 -> 1266500 | ... N13: =N6-N11 -> 2086500 | O13: =SUM(C13:N13) -> 13108000
B15: 【年次の税金（翌期納付＝現金の引当が必要）】
B16: 消費税（簡易課税） | C16: 売上消費税×(1−みなし50%) | O16: =O6*前提!$C$24*(1-前提!$C$23) -> 765500
B17: 法人税等 | C17: 利益×実効税率 と 均等割 の大きい方 | O17: =MAX(前提!$C$26,O13*前提!$C$25) -> 3277000
B18: 税引後利益 | O18: =O13-O17 -> 9831000
B19: ★引当てる税金合計（別口座へ） | C19: この現金は「使ってはいけない」 | O19: =O16+O17 -> 4042500

Sheet CF_現金_Y1
B2: Year1 月次 キャッシュフロー（税金引当込み）
B3: 「手元現金」と「税金を避けた後の“本当に使える現金”」を分けて表示。納付月の事故を防ぐ。
B5: 項目 | C5: 1月 | D5: 2月 | E5: 3月 | F5: 4月 | G5: 5月 | H5: 6月 | I5: 7月 | J5: 8月 | K5: 9月 | L5: 10月 | M5: 11月 | N5: 12月
B6: 営業利益（月次） | C6: =PL_損益_Y1!C13 -> 316500 | D6: =PL_損益_Y1!D13 -> 316500 | E6: =PL_損益_Y1!E13 -> 316500 | F6: =PL_損益_Y1!F13 -> 316500 | G6: =PL_損益_Y1!G13 -> 966500 | H6: =PL_損益_Y1!H13 -> 966500 | I6: =PL_損益_Y1!I13 -> 966500 | J6: =PL_損益_Y1!J13 -> 1266500 | ... N6: =PL_損益_Y1!N13 -> 2086500
B7: 手元現金 残高 | C7: =前提!$C$6+C6 -> 2316500 | D7: =C7+D6 -> 2633000 | E7: =D7+E6 -> 2949500 | F7: =E7+F6 -> 3266000 | G7: =F7+G6 -> 4232500 | H7: =G7+H6 -> 5199000 | I7: =H7+I6 -> 6165500 | J7: =I7+J6 -> 7432000 | K7: =J7+K6 -> 9148500 | ... N7: =M7+N6 -> 15108000
B9: 累計 税金引当（避ける額） | C9: =PL_損益_Y1!$O$19/12*1 -> 336875 | D9: =PL_損益_Y1!$O$19/12*2 -> 673750 | E9: =PL_損益_Y1!$O$19/12*3 -> 1010625 | F9: =PL_損益_Y1!$O$19/12*4 -> 1347500 | G9: =PL_損益_Y1!$O$19/12*5 -> 1684375 | H9: =PL_損益_Y1!$O$19/12*6 -> 2021250 | I9: =PL_損益_Y1!$O$19/12*7 -> 2358125 | J9: =PL_損益_Y1!$O$19/12*8 -> 2695000 | K9: =PL_損益_Y1!$O$19/12*9 -> 3031875 | L9: =PL_損益_Y1!$O$19/12*10 -> 3368750 | M9: =PL_損益_Y1!$O$19/12*11 -> 3705625 | N9: =PL_損益_Y1!$O$19/12*12 -> 4042500
B10: ★本当に使える現金 | C10: =C7-C9 -> 1979625 | D10: =D7-D9 -> 1959250 | E10: =E7-E9 -> 1938875 | F10: =F7-F9 -> 1918500 | G10: =G7-G9 -> 2548125 | H10: =H7-H9 -> 3177750 | I10: =I7-I9 -> 3807375 | J10: =J7-J9 -> 4737000 | ... N10: =N7-N9 -> 11065500
B12: 年末 手元現金 | C12: =N7 -> 15108000
B13: 年末 本当に使える現金（税引当後） | C13: =N10 -> 11065500
B14: 本当に使える現金の最低値（底） | C14: =MIN(C10:N10) -> 1918500 | D14: ← ここがプラスなら、税金を避けても資金は尽きない

Sheet 営業ファネル_Y1
B2: Year1 営業ファネル — 登壇・自前コンテンツ版（受注に必要な活動量）
B3: 「診断を何件取る」の裏で、毎月何回 登壇/発信が要るかを逆算。営業時間が週1日に収まるかを検証。
B5: 項目 | C5: 1月 | D5: 2月 | E5: 3月 | F5: 4月 | G5: 5月 | H5: 6月 | I5: 7月 | J5: 8月 | K5: 9月 | L5: 10月 | M5: 11月 | N5: 12月
B6: 新規診断 目標（件） | C6: =Year1_月次!C6+Year1_月次!C7 -> 1 | D6: =Year1_月次!D6+Year1_月次!D7 -> 1 | E6: =Year1_月次!E6+Year1_月次!E7 -> 1 | F6: =Year1_月次!F6+Year1_月次!F7 -> 1 | G6: =Year1_月次!G6+Year1_月次!G7 -> 0 | H6: =Year1_月次!H6+Year1_月次!H7 -> 0 | I6: =Year1_月次!I6+Year1_月次!I7 -> 0 | J6: =Year1_月次!J6+Year1_月次!J7 -> 1 | ... N6: =Year1_月次!N6+Year1_月次!N7 -> 1
B7: 必要 無料相談（件） | C7: =C6/前提!$C$31 -> 2.8571429 | D7: =D6/前提!$C$31 -> 2.8571429 | E7: =E6/前提!$C$31 -> 2.8571429 | F7: =F6/前提!$C$31 -> 2.8571429 | G7: =G6/前提!$C$31 -> 0 | H7: =H6/前提!$C$31 -> 0 | I7: =I6/前提!$C$31 -> 0 | J7: =J6/前提!$C$31 -> 2.8571429 | ... N7: =N6/前提!$C$31 -> 2.8571429
B8: 必要 登壇回数（回） | C8: =C7/(前提!$C$29*前提!$C$30) -> 0.95238095 | D8: =D7/(前提!$C$29*前提!$C$30) -> 0.95238095 | E8: =E7/(前提!$C$29*前提!$C$30) -> 0.95238095 | F8: =F7/(前提!$C$29*前提!$C$30) -> 0.95238095 | G8: =G7/(前提!$C$29*前提!$C$30) -> 0 | H8: =H7/(前提!$C$29*前提!$C$30) -> 0 | I8: =I7/(前提!$C$29*前提!$C$30) -> 0 | J8: =J7/(前提!$C$29*前提!$C$30) -> 0.95238095 | ... N8: =N7/(前提!$C$29*前提!$C$30) -> 0.95238095
B10: 営業 所要時間（h/月） | C10: =C8*前提!$C$33 -> 9.5238095 | D10: =D8*前提!$C$33 -> 9.5238095 | E10: =E8*前提!$C$33 -> 9.5238095 | F10: =F8*前提!$C$33 -> 9.5238095 | G10: =G8*前提!$C$33 -> 0 | H10: =H8*前提!$C$33 -> 0 | I10: =I8*前提!$C$33 -> 0 | J10: =J8*前提!$C$33 -> 9.5238095 | ... N10: =N8*前提!$C$33 -> 9.5238095
B11: （参考）想定 伴走新規（社） | C11: =C6*前提!$C$32 -> 0.5 | D11: =D6*前提!$C$32 -> 0.5 | E11: =E6*前提!$C$32 -> 0.5 | F11: =F6*前提!$C$32 -> 0.5 | G11: =G6*前提!$C$32 -> 0 | H11: =H6*前提!$C$32 -> 0 | I11: =I6*前提!$C$32 -> 0 | J11: =J6*前提!$C$32 -> 0.5 | ... N11: =N6*前提!$C$32 -> 0.5
B13: 年間 必要アプローチ 合計 | C13: =SUM(C8:N8) -> 6.6666667
B14: 月平均 営業時間 | C14: =AVERAGE(C10:N10) -> 5.5555556 | D14: ← これが週の使える営業時間に収まるかを見る（目安：週1日＝月約32h）
B16: （注）1登壇 ≒ 参加者×相談化率×成約率 の診断を生む。初回登壇は資料作成+集客で別途約20hの先行投資。

Sheet 個人サバイバル
B2: 個人サバイバル — 会社とは別の“あなたの財布”
B3: 役員報酬7万では生活費に届かない。差額を貯蓄で何ヶ月もたせられるか。これが本当の滑走路。
B5: 個人の貯蓄（滑走路） | C5: =前提!$C$35 -> 2000000
B6: 個人の生活費（月） | C6: =前提!$C$36 -> 500000
B7: 役員報酬（手取り≒額面） | C7: =前提!$C$20 -> 70000 | D7: 概算。実際は所得税・社保で少し減る
B8: 月の不足額（生活費−報酬） | C8: =C6-C7 -> 430000 | D8: 貯蓄から毎月出ていく額
B9: 個人サバイバル月数 | C9: =IF(C8<=0,999,C5/C8) -> 4.6511628 | D9: 貯蓄が尽きるまでの月数
B11: 【意味】
B12: ・役員報酬を7万に下げると、会社の損益分岐は約18万に激減。既存受託40万だけで会社は黒字。
B13: ・つまり会社はすぐ黒字化し、貯蓄200万は会社の延命には使わない。
B14: ・本当の制約は「あなた個人」。生活費50万−報酬7万＝月43万を、貯蓄200万で約4.6ヶ月もたせる勝負。
B15: ・新規売上が立って会社に利益が貯まったら、Y2で役員報酬を上げて貯蓄の取り崩しを止める。
B16: ・注意：報酬を極端に下げると会社利益が増え法人税も増える。立ち上げ期の“現金温存”としては正しいが、
B17: 軌道に乗ったら「法人税＋所得税＋社保」の合計が最小になる報酬額に最適化する。

Sheet PL_3年
B2: 3年 損益計算書（年次・会計レベル）
B3: Y1=PL_損益_Y1（月次積上）／Y2・Y3=3年_四半期 の計画数量から自動リンク。役員報酬は7万据置（→Y2最適化は別タスク）。
B5: 項目 | C5: Year1 | D5: Year2 | E5: Year3
B6: 売上高（税抜） | C6: =PL_損益_Y1!O6 -> 15310000 | D6: ='3年_四半期'!D22 -> 28140000 | E6: ='3年_四半期'!E22 -> 30300000
B7: 費用合計（役員報酬+社保+販管） | C7: =PL_損益_Y1!O11 -> 2202000 | D7: =前提!C7*12 -> 2202000 | E7: =前提!C7*12 -> 2202000
B8: 営業利益（税引前） | C8: =C6-C7 -> 13108000 | D8: =D6-D7 -> 25938000 | E8: =E6-E7 -> 28098000
B9: 消費税（簡易課税） | C9: =C6*前提!C24*(1-前提!C23) -> 765500 | D9: =D6*前提!C24*(1-前提!C23) -> 1407000 | E9: =E6*前提!C24*(1-前提!C23) -> 1515000
B10: 法人税等 | C10: =MAX(前提!C26,C8*前提!C25) -> 3277000 | D10: =MAX(前提!C26,D8*前提!C25) -> 6484500 | E10: =MAX(前提!C26,E8*前提!C25) -> 7024500
B11: 税引後利益 | C11: =C8-C10 -> 9831000 | D11: =D8-D10 -> 19453500 | E11: =E8-E10 -> 21073500
B12: ★引当てる税金合計（消費税+法人税・別口座） | C12: =C9+C10 -> 4042500 | D12: =D9+D10 -> 7891500 | E12: =E9+E10 -> 8539500
B14: 注：Y2/Y3は役員報酬7万据置のため営業利益が過大→法人税も過大。Y2で役員報酬を上げると法人税は大きく下がる（役員報酬最適化タスク）。

Sheet BS_Y1末
B2: Year1末 貸借対照表（B/S・簡易）
B3: 現金=CF_現金_Y1末／繰越利益剰余金=PL税引後利益。黄色＝仮の入力（要・実態確認）。差額チェックが0なら貸借一致。
B5: 【仮の前提（黄色）】
B6: 資本金（登記値・仮） | C6: 1000000 | D6: 滑走路200万の内、出資した額。残りは役員借入とみなす
B8: 【資産の部】
B9: 現金預金 | C9: =CF_現金_Y1!N7 -> 15108000
B10: 売掛金 | C10: 0 | D10: 当月入金前提＝0。翌月入金なら12月売上の1ヶ月分を入れる
B11: 資産合計 | C11: =C9+C10 -> 15108000
B13: 【負債の部】
B14: 役員借入金 | C14: =前提!C6-C6 -> 1000000 | D14: 滑走路200万−資本金。海外資金が出資なら0に
B15: 未払法人税等（翌期納付） | C15: =PL_損益_Y1!O17 -> 3277000
B16: 負債合計 | C16: =C14+C15 -> 4277000
B18: 【純資産の部】
B19: 資本金 | C19: =C6 -> 1000000
B20: 繰越利益剰余金（当期税引後利益） | C20: =PL_損益_Y1!O18 -> 9831000
B21: 純資産合計 | C21: =C19+C20 -> 10831000
B23: 負債・純資産合計 | C23: =C16+C21 -> 15108000
B24: 差額チェック（資産−負債純資産） | C24: =C11-C23 -> 0 | D24: ← 0 なら貸借一致
B26: 【メモ】翌期納付の消費税（避ける現金・税抜現金モデルのため負債計上せず別管理） | C26: =PL_損益_Y1!O16 -> 765500
B28: ※簡易B/S：売上を税抜現金で計上する既存モデルに合わせ、消費税はメモ管理。厳密な税込キャッシュ化／Y2・Y3末ロールBSは次の拡張で。

Sheet 感度_伴走
B2: 感度分析：濃い伴走 月75万 vs 50万（Year1）
B3: 伴走の月額単価だけを変えたときの、総売上・利益・税・年末現金の差。黄色＝低単価の入力。
B5: 伴走 標準単価（前提!C13） | C5: =前提!C13 -> 750000
B6: 伴走 低単価（感度・黄色） | C6: 500000
B7: 伴走の社月合計（Year1） | C7: =SUM(Year1_月次!C8:N8) -> 12 | D7: 稼働社数×月の合計
B8: 売上差（低−標準） | C8: =C7*(C6-C5) -> -3000000
B10: 項目 | C10: 標準（75万） | D10: 低（50万）
B11: 年間総売上 | C11: =PL_損益_Y1!O6 -> 15310000 | D11: =C11+C8 -> 12310000
B12: 営業利益（税引前） | C12: =PL_損益_Y1!O13 -> 13108000 | D12: =C12+C8 -> 10108000
B13: 法人税等 | C13: =MAX(前提!C26,C12*前提!C25) -> 3277000 | D13: =MAX(前提!C26,D12*前提!C25) -> 2527000
B14: 税引後利益 | C14: =C12-C13 -> 9831000 | D14: =D12-D13 -> 7581000
B15: 消費税（簡易） | C15: =C11*前提!C24*(1-前提!C23) -> 765500 | D15: =D11*前提!C24*(1-前提!C23) -> 615500
B16: 年末現金（手元） | C16: =前提!C6+C12 -> 15108000 | D16: =前提!C6+D12 -> 12108000
B18: 読み：50万に下げると年末現金が約300万薄くなる。介護の薄利には50万が現実的だが、補助金で自己負担が下がるなら75万維持も可（subsidy-research参照）。
