Workbook

Sheet 前提
B2: 伴走事業 — 経営シミュレーション
B3: 前提（青い数字を打ち替えると、全シートが自動で再計算されます）
B5: ① 滑走路とコスト
B6: 初期キャッシュ（滑走路） | C6: 2000000 | D6: 海外資金の引き出し。月50万×4ヶ月分
B7: 会社の月次固定費（損益分岐） | C7: =C20+C21+C22 | D7: 役員報酬+社保+販管費の自動計算。これを総売上が超えれば会社は黒字
B8: 既存受託（月・当面継続） | C8: 400000 | D8: 立ち上げ期の土台。新事業が育つまでの足場
B10: ② 商品単価
B11: 構造診断・立ち上げ価格 | C11: 100000 | D11: 先着5社の実績協力価格（通常30万）
B12: 構造診断・通常価格 | C12: 300000 | D12: 竹（標準）。松は50万〜
B13: 濃い伴走（月額・1社） | C13: 750000 | D13: 週2日相当。シナリオA
B14: ライト契約（月額・1社） | C14: 70000 | D14: 自走後の継続。相談・保守ベース
B16: ③ 上限（品質を守る方針）
B17: 濃い伴走の同時上限（社） | C17: 3 | D17: 3社を超えると文脈維持の工数が品質を割る
B19: ④ 会計レベル前提（費用・税）
B20: 役員報酬（月） | C20: 70000 | D20: 立ち上げ年は7万で低く固定（定期同額のため期中変更は不可→Y2で増額）。生活は貯蓄で橋渡し
B21: 会社負担 社会保険（月） | C21: 11000 | D21: 役員報酬7万の最低等級 概算
B22: 販管費（月） | C22: 102500 | D22: 税理士・SaaS・通信・交通・交際・学習・広告の合算
B23: 消費税 みなし仕入率（簡易課税） | C23: 0.5 | D23: サービス業=第5種50%。納税=売上消費税×(1-この率)
B24: 消費税率 | C24: 0.1
B25: 法人実効税率（概算） | C25: 0.25 | D25: 所得800万以下の中小法人 概算
B26: 法人住民税 均等割（年・赤字でも発生） | C26: 70000 | D26: 最低限かかる固定税
B28: ⑤ 営業ファネル（登壇・自前コンテンツで新規診断を生む）
B29: 1登壇あたり参加者（人） | C29: 20 | D29: 小規模セミナー/勉強会の集客想定。最初の1〜2回はここが一番難所（要・自前集客）
B30: 参加者→無料相談 化率 | C30: 0.15 | D30: 登壇を聞いた人が個別相談に来る率。温度が高い10〜20%
B31: 無料相談→診断 成約率 | C31: 0.35 | D31: 登壇経由は信頼が乗り30万診断に進みやすい(コールドの28%より高い)
B32: 診断→伴走 移行率 | C32: 0.5 | D32: 断る関門として意図的に絞る。据え置き
B33: 1登壇の所要時間（h/回・定常） | C33: 10 | D33: 資料作成は流用前提。初回のみ別途+約20hの先行投資(ストック資産化＝L-3/L-4)
B34: ⑥ 個人サバイバル（会社とは別の財布）
B35: 個人の貯蓄（滑走路） | C35: 2000000 | D35: 海外資金。会社でなく“あなた個人”の生活を支える
B36: 個人の生活費（月） | C36: 500000 | D36: 家賃・生活・税社保等の個人支出

Sheet Year1_月次
B2: Year 1 — 月次キャッシュ推移
B3: 新事業の「数量」だけ青で打ち替えてください（診断件数・伴走社数・ライト社数）。売上と残高は自動計算。
B5: 項目 | C5: 1月 | D5: 2月 | E5: 3月 | F5: 4月 | G5: 5月 | H5: 6月 | I5: 7月 | J5: 8月 | K5: 9月 | L5: 10月 | M5: 11月 | N5: 12月 | O5: 12月
B6: 診断・件数（立ち上げ価格） | C6: 1 | D6: 1 | E6: 1 | F6: 1 | G6: 0 | H6: 0 | I6: 0 | J6: 0 | K6: 0 | L6: 0 | M6: 0 | N6: 0
B7: 診断・件数（通常価格） | C7: 0 | D7: 0 | E7: 0 | F7: 0 | G7: 0 | H7: 0 | I7: 0 | J7: 1 | K7: 0 | L7: 1 | M7: 0 | N7: 1
B8: 濃い伴走・稼働社数 | C8: 0 | D8: 0 | E8: 0 | F8: 0 | G8: 1 | H8: 1 | I8: 1 | J8: 1 | K8: 2 | L8: 2 | M8: 2 | N8: 2
B9: ライト契約・社数 | C9: 0 | D9: 0 | E9: 0 | F9: 0 | G9: 0 | H9: 0 | I9: 0 | J9: 0 | K9: 0 | L9: 1 | M9: 1 | N9: 1
B11: 新事業 売上 | C11: =C6*前提!$C$11+C7*前提!$C$12+C8*前提!$C$13+C9*前提!$C$14 | D11: =D6*前提!$C$11+D7*前提!$C$12+D8*前提!$C$13+D9*前提!$C$14 | E11: =E6*前提!$C$11+E7*前提!$C$12+E8*前提!$C$13+E9*前提!$C$14 | F11: =F6*前提!$C$11+F7*前提!$C$12+F8*前提!$C$13+F9*前提!$C$14 | G11: =G6*前提!$C$11+G7*前提!$C$12+G8*前提!$C$13+G9*前提!$C$14 | H11: =H6*前提!$C$11+H7*前提!$C$12+H8*前提!$C$13+H9*前提!$C$14 | I11: =I6*前提!$C$11+I7*前提!$C$12+I8*前提!$C$13+I9*前提!$C$14 | J11: =J6*前提!$C$11+J7*前提!$C$12+J8*前提!$C$13+J9*前提!$C$14 | ... N11: =N6*前提!$C$11+N7*前提!$C$12+N8*前提!$C$13+N9*前提!$C$14
B12: 既存受託 | C12: =前提!$C$8 | D12: =前提!$C$8 | E12: =前提!$C$8 | F12: =前提!$C$8 | G12: =前提!$C$8 | H12: =前提!$C$8 | I12: =前提!$C$8 | J12: =前提!$C$8 | ... N12: =前提!$C$8
B13: 総売上 | C13: =C11+C12 | D13: =D11+D12 | E13: =E11+E12 | F13: =F11+F12 | G13: =G11+G12 | H13: =H11+H12 | I13: =I11+I12 | J13: =J11+J12 | ... N13: =N11+N12
B15: 損益分岐点 | C15: =前提!$C$7 | D15: =前提!$C$7 | E15: =前提!$C$7 | F15: =前提!$C$7 | G15: =前提!$C$7 | H15: =前提!$C$7 | I15: =前提!$C$7 | J15: =前提!$C$7 | ... N15: =前提!$C$7
B16: 単月収支（±） | C16: =C13-C15 | D16: =D13-D15 | E16: =E13-E15 | F16: =F13-F15 | G16: =G13-G15 | H16: =H13-H15 | I16: =I13-I15 | J16: =J13-J15 | ... N16: =N13-N15
B17: キャッシュ残高 | C17: =前提!$C$6+C16 | D17: =C17+D16 | E17: =D17+E16 | F17: =E17+F16 | G17: =F17+G16 | H17: =G17+H16 | I17: =H17+I16 | J17: =I17+J16 | K17: =J17+K16 | ... N17: =M17+N16
B19: 年間 新事業売上 合計 | C19: =SUM(C11:N11)
B20: 年末キャッシュ残高 | C20: =N17
B21: 初年度の最低残高（滑走路の底） | C21: =MIN(C17:N17) | D21: ← ここがマイナスにならなければ、負の連鎖で死ぬことはない

Sheet 3年_四半期
B2: 3年計画 — 四半期ショートスパン
B3: 見るのは4つだけ：診断数・伴走社数・ライト社数・キャッシュ残高。指標を増やさないのが一人会社のコツ。
B5: 項目 | C5: Y1Q1 | D5: Y1Q2 | E5: Y1Q3 | F5: Y1Q4 | G5: Y2Q1 | H5: Y2Q2 | I5: Y2Q3 | J5: Y2Q4 | K5: Y3Q1 | L5: Y3Q2 | M5: Y3Q3 | N5: Y3Q4
B6: 診断・件数 / 四半期 | C6: 3 | D6: 2 | E6: 2 | F6: 2 | G6: 2 | H6: 2 | I6: 2 | J6: 2 | K6: 1 | L6: 1 | M6: 1 | N6: 1
B7: 濃い伴走・社数（平均） | C7: 0 | D7: 1 | E7: 1.5 | F7: 2 | G7: 2 | H7: 2 | I7: 2 | J7: 2 | K7: 2 | L7: 2 | M7: 2 | N7: 2
B8: ライト・社数 | C8: 0 | D8: 0 | E8: 0 | F8: 1 | G8: 2 | H8: 3 | I8: 4 | J8: 5 | K8: 6 | L8: 7 | M8: 8 | N8: 9
B10: 新事業 売上 / Q | C10: =C6*前提!$C$11+C7*前提!$C$13*3+C8*前提!$C$14*3 | D10: =D6*前提!$C$11+D7*前提!$C$13*3+D8*前提!$C$14*3 | E10: =E6*前提!$C$12+E7*前提!$C$13*3+E8*前提!$C$14*3 | F10: =F6*前提!$C$12+F7*前提!$C$13*3+F8*前提!$C$14*3 | G10: =G6*前提!$C$12+G7*前提!$C$13*3+G8*前提!$C$14*3 | H10: =H6*前提!$C$12+H7*前提!$C$13*3+H8*前提!$C$14*3 | I10: =I6*前提!$C$12+I7*前提!$C$13*3+I8*前提!$C$14*3 | J10: =J6*前提!$C$12+J7*前提!$C$13*3+J8*前提!$C$14*3 | K10: =K6*前提!$C$12+K7*前提!$C$13*3+K8*前提!$C$14*3 | L10: =L6*前提!$C$12+L7*前提!$C$13*3+L8*前提!$C$14*3 | ... N10: =N6*前提!$C$12+N7*前提!$C$13*3+N8*前提!$C$14*3
B11: 既存受託 / Q | C11: =前提!$C$8*3 | D11: =前提!$C$8*3 | E11: =前提!$C$8*3 | F11: =前提!$C$8*3 | G11: =前提!$C$8*3 | H11: =前提!$C$8*3 | I11: =前提!$C$8*3 | J11: =前提!$C$8*3 | ... N11: =前提!$C$8*3
B12: 総売上 / Q | C12: =C10+C11 | D12: =D10+D11 | E12: =E10+E11 | F12: =F10+F11 | G12: =G10+G11 | H12: =H10+H11 | I12: =I10+I11 | J12: =J10+J11 | ... N12: =N10+N11
B13: 損益分岐 / Q | C13: =前提!$C$7*3 | D13: =前提!$C$7*3 | E13: =前提!$C$7*3 | F13: =前提!$C$7*3 | G13: =前提!$C$7*3 | H13: =前提!$C$7*3 | I13: =前提!$C$7*3 | J13: =前提!$C$7*3 | ... N13: =前提!$C$7*3
B14: 四半期 収支（±） | C14: =C12-C13 | D14: =D12-D13 | E14: =E12-E13 | F14: =F12-F13 | G14: =G12-G13 | H14: =H12-H13 | I14: =I12-I13 | J14: =J12-J13 | ... N14: =N12-N13
B15: 四半期末 キャッシュ残高 | C15: =前提!$C$6+C14 | D15: =C15+D14 | E15: =D15+E14 | F15: =E15+F14 | G15: =F15+G14 | H15: =G15+H14 | I15: =H15+I14 | J15: =I15+J14 | K15: =J15+K14 | ... N15: =M15+N14
B17: 年間総売上 | C17: =SUM(C12:F12) | D17: =SUM(G12:J12) | E17: =SUM(K12:N12)
B18: （C列=Year1, D列=Year2, E列=Year3 の合計）
B22: 年間総売上（C=Y1 / D=Y2 / E=Y3） | C22: =SUM(C12:F12) | D22: =SUM(G12:J12) | E22: =SUM(K12:N12)

Sheet 読み方
B2: このモデルの読み方
B4: ■ 何を打ち替えればいいか
B5: ・黄色いセル（青字）だけを変えてください。黒字は自動計算なので触らない。
B6: ・「前提」シートで単価・分岐点・滑走路を変えると、全シートに反映されます。
B7: ・「Year1_月次」「3年_四半期」では、各月/各Qの "数量"（診断件数・伴走社数・ライト社数）を変えます。
B9: ■ どこを見れば「死なない」と分かるか
B10: ・Year1_月次シートの「初年度の最低残高（滑走路の底）」。ここがプラスなら、負の連鎖で資金が尽きることはありません。
B11: ・現在の慎重シナリオでは、底は初月の約190万円。初期200万からほぼ減らずに立ち上がります。
B13: ■ この事業の構造的な強み（数字が示すこと）
B14: ・損益分岐 月50万に対し、既存受託が月40万。埋めるべき差は月10万だけ。
B15: ・診断1社（10万）でその月は分岐点に到達。伴走1社（月75万）に上がれば即黒字。ハードルは低い。
B16: ・濃い伴走は上限3社（品質方針）。3社目以降は売上でなく、資産化・ライト層・1対Nで伸ばす設計。
... B21: ・売上の上振れより、滑走路を守る判断を優先。筋の通らない案件を承認欲で取らない（判断基準に戻る）。

Sheet PL_損益_Y1
B2: Year1 月次 損益計算書（P/L）
B3: 売上は「Year1_月次」から自動リンク（緑字）。費用は「前提」から。消費税は預かりのため売上から除外＝税抜ベース。
B5: 項目 | C5: 1月 | D5: 2月 | E5: 3月 | F5: 4月 | G5: 5月 | H5: 6月 | I5: 7月 | J5: 8月 | K5: 9月 | L5: 10月 | M5: 11月 | N5: 12月 | O5: 年計
B6: 売上高（税抜） | C6: =Year1_月次!C13 | D6: =Year1_月次!D13 | E6: =Year1_月次!E13 | F6: =Year1_月次!F13 | G6: =Year1_月次!G13 | H6: =Year1_月次!H13 | I6: =Year1_月次!I13 | J6: =Year1_月次!J13 | ... N6: =Year1_月次!N13 | O6: =SUM(C6:N6)
B8: 役員報酬 | C8: =前提!$C$20 | D8: =前提!$C$20 | E8: =前提!$C$20 | F8: =前提!$C$20 | G8: =前提!$C$20 | H8: =前提!$C$20 | I8: =前提!$C$20 | J8: =前提!$C$20 | ... N8: =前提!$C$20 | O8: =SUM(C8:N8)
B9: 法定福利費（社保・会社） | C9: =前提!$C$21 | D9: =前提!$C$21 | E9: =前提!$C$21 | F9: =前提!$C$21 | G9: =前提!$C$21 | H9: =前提!$C$21 | I9: =前提!$C$21 | J9: =前提!$C$21 | ... N9: =前提!$C$21 | O9: =SUM(C9:N9)
B10: 販管費 | C10: =前提!$C$22 | D10: =前提!$C$22 | E10: =前提!$C$22 | F10: =前提!$C$22 | G10: =前提!$C$22 | H10: =前提!$C$22 | I10: =前提!$C$22 | J10: =前提!$C$22 | ... N10: =前提!$C$22 | O10: =SUM(C10:N10)
B11: 費用 合計 | C11: =C8+C9+C10 | D11: =D8+D9+D10 | E11: =E8+E9+E10 | F11: =F8+F9+F10 | G11: =G8+G9+G10 | H11: =H8+H9+H10 | I11: =I8+I9+I10 | J11: =J8+J9+J10 | ... N11: =N8+N9+N10 | O11: =SUM(C11:N11)
B13: 営業利益（税引前） | C13: =C6-C11 | D13: =D6-D11 | E13: =E6-E11 | F13: =F6-F11 | G13: =G6-G11 | H13: =H6-H11 | I13: =I6-I11 | J13: =J6-J11 | ... N13: =N6-N11 | O13: =SUM(C13:N13)
B15: 【年次の税金（翌期納付＝現金の引当が必要）】
B16: 消費税（簡易課税） | C16: 売上消費税×(1−みなし50%) | O16: =O6*前提!$C$24*(1-前提!$C$23)
B17: 法人税等 | C17: 利益×実効税率 と 均等割 の大きい方 | O17: =MAX(前提!$C$26,O13*前提!$C$25)
B18: 税引後利益 | O18: =O13-O17
B19: ★引当てる税金合計（別口座へ） | C19: この現金は「使ってはいけない」 | O19: =O16+O17

Sheet CF_現金_Y1
B2: Year1 月次 キャッシュフロー（税金引当込み）
B3: 「手元現金」と「税金を避けた後の“本当に使える現金”」を分けて表示。納付月の事故を防ぐ。
B5: 項目 | C5: 1月 | D5: 2月 | E5: 3月 | F5: 4月 | G5: 5月 | H5: 6月 | I5: 7月 | J5: 8月 | K5: 9月 | L5: 10月 | M5: 11月 | N5: 12月
B6: 営業利益（月次） | C6: =PL_損益_Y1!C13 | D6: =PL_損益_Y1!D13 | E6: =PL_損益_Y1!E13 | F6: =PL_損益_Y1!F13 | G6: =PL_損益_Y1!G13 | H6: =PL_損益_Y1!H13 | I6: =PL_損益_Y1!I13 | J6: =PL_損益_Y1!J13 | ... N6: =PL_損益_Y1!N13
B7: 手元現金 残高 | C7: =前提!$C$6+C6 | D7: =C7+D6 | E7: =D7+E6 | F7: =E7+F6 | G7: =F7+G6 | H7: =G7+H6 | I7: =H7+I6 | J7: =I7+J6 | K7: =J7+K6 | ... N7: =M7+N6
B9: 累計 税金引当（避ける額） | C9: =PL_損益_Y1!$O$19/12*1 | D9: =PL_損益_Y1!$O$19/12*2 | E9: =PL_損益_Y1!$O$19/12*3 | F9: =PL_損益_Y1!$O$19/12*4 | G9: =PL_損益_Y1!$O$19/12*5 | H9: =PL_損益_Y1!$O$19/12*6 | I9: =PL_損益_Y1!$O$19/12*7 | J9: =PL_損益_Y1!$O$19/12*8 | K9: =PL_損益_Y1!$O$19/12*9 | L9: =PL_損益_Y1!$O$19/12*10 | M9: =PL_損益_Y1!$O$19/12*11 | N9: =PL_損益_Y1!$O$19/12*12
B10: ★本当に使える現金 | C10: =C7-C9 | D10: =D7-D9 | E10: =E7-E9 | F10: =F7-F9 | G10: =G7-G9 | H10: =H7-H9 | I10: =I7-I9 | J10: =J7-J9 | ... N10: =N7-N9
B12: 年末 手元現金 | C12: =N7
B13: 年末 本当に使える現金（税引当後） | C13: =N10
B14: 本当に使える現金の最低値（底） | C14: =MIN(C10:N10) | D14: ← ここがプラスなら、税金を避けても資金は尽きない

Sheet 営業ファネル_Y1
B2: Year1 営業ファネル — 登壇・自前コンテンツ版（受注に必要な活動量）
B3: 「診断を何件取る」の裏で、毎月何回 登壇/発信が要るかを逆算。営業時間が週1日に収まるかを検証。
B5: 項目 | C5: 1月 | D5: 2月 | E5: 3月 | F5: 4月 | G5: 5月 | H5: 6月 | I5: 7月 | J5: 8月 | K5: 9月 | L5: 10月 | M5: 11月 | N5: 12月
B6: 新規診断 目標（件） | C6: =Year1_月次!C6+Year1_月次!C7 | D6: =Year1_月次!D6+Year1_月次!D7 | E6: =Year1_月次!E6+Year1_月次!E7 | F6: =Year1_月次!F6+Year1_月次!F7 | G6: =Year1_月次!G6+Year1_月次!G7 | H6: =Year1_月次!H6+Year1_月次!H7 | I6: =Year1_月次!I6+Year1_月次!I7 | J6: =Year1_月次!J6+Year1_月次!J7 | ... N6: =Year1_月次!N6+Year1_月次!N7
B7: 必要 無料相談（件） | C7: =C6/前提!$C$31 | D7: =D6/前提!$C$31 | E7: =E6/前提!$C$31 | F7: =F6/前提!$C$31 | G7: =G6/前提!$C$31 | H7: =H6/前提!$C$31 | I7: =I6/前提!$C$31 | J7: =J6/前提!$C$31 | ... N7: =N6/前提!$C$31
B8: 必要 登壇回数（回） | C8: =C7/(前提!$C$29*前提!$C$30) | D8: =D7/(前提!$C$29*前提!$C$30) | E8: =E7/(前提!$C$29*前提!$C$30) | F8: =F7/(前提!$C$29*前提!$C$30) | G8: =G7/(前提!$C$29*前提!$C$30) | H8: =H7/(前提!$C$29*前提!$C$30) | I8: =I7/(前提!$C$29*前提!$C$30) | J8: =J7/(前提!$C$29*前提!$C$30) | ... N8: =N7/(前提!$C$29*前提!$C$30)
B10: 営業 所要時間（h/月） | C10: =C8*前提!$C$33 | D10: =D8*前提!$C$33 | E10: =E8*前提!$C$33 | F10: =F8*前提!$C$33 | G10: =G8*前提!$C$33 | H10: =H8*前提!$C$33 | I10: =I8*前提!$C$33 | J10: =J8*前提!$C$33 | ... N10: =N8*前提!$C$33
B11: （参考）想定 伴走新規（社） | C11: =C6*前提!$C$32 | D11: =D6*前提!$C$32 | E11: =E6*前提!$C$32 | F11: =F6*前提!$C$32 | G11: =G6*前提!$C$32 | H11: =H6*前提!$C$32 | I11: =I6*前提!$C$32 | J11: =J6*前提!$C$32 | ... N11: =N6*前提!$C$32
B13: 年間 必要アプローチ 合計 | C13: =SUM(C8:N8)
B14: 月平均 営業時間 | C14: =AVERAGE(C10:N10) | D14: ← これが週の使える営業時間に収まるかを見る（目安：週1日＝月約32h）
B16: （注）1登壇 ≒ 参加者×相談化率×成約率 の診断を生む。初回登壇は資料作成+集客で別途約20hの先行投資。

Sheet 個人サバイバル
B2: 個人サバイバル — 会社とは別の“あなたの財布”
B3: 役員報酬7万では生活費に届かない。差額を貯蓄で何ヶ月もたせられるか。これが本当の滑走路。
B5: 個人の貯蓄（滑走路） | C5: =前提!$C$35
B6: 個人の生活費（月） | C6: =前提!$C$36
B7: 役員報酬（手取り≒額面） | C7: =前提!$C$20 | D7: 概算。実際は所得税・社保で少し減る
B8: 月の不足額（生活費−報酬） | C8: =C6-C7 | D8: 貯蓄から毎月出ていく額
B9: 個人サバイバル月数 | C9: =IF(C8<=0,999,C5/C8) | D9: 貯蓄が尽きるまでの月数
B11: 【意味】
B12: ・役員報酬を7万に下げると、会社の損益分岐は約18万に激減。既存受託40万だけで会社は黒字。
B13: ・つまり会社はすぐ黒字化し、貯蓄200万は会社の延命には使わない。
B14: ・本当の制約は「あなた個人」。生活費50万−報酬7万＝月43万を、貯蓄200万で約4.6ヶ月もたせる勝負。
B15: ・新規売上が立って会社に利益が貯まったら、Y2で役員報酬を上げて貯蓄の取り崩しを止める。
B16: ・注意：報酬を極端に下げると会社利益が増え法人税も増える。立ち上げ期の“現金温存”としては正しいが、
B17: 軌道に乗ったら「法人税＋所得税＋社保」の合計が最小になる報酬額に最適化する。
